README.md
setup.cfg
setup.py
keras_sequential_ascii/__init__.py
keras_sequential_ascii/main.py
keras_sequential_ascii.egg-info/PKG-INFO
keras_sequential_ascii.egg-info/SOURCES.txt
keras_sequential_ascii.egg-info/dependency_links.txt
keras_sequential_ascii.egg-info/requires.txt
keras_sequential_ascii.egg-info/top_level.txt