Metadata-Version: 1.1
Name: keras-sequential-ascii
Version: 0.1.1
Summary: ASCII summary for simple sequential models in Keras
Home-page: https://github.com/stared/keras-sequential-ascii
Author: Piotr Migdał
Author-email: pmigdal@gmail.com
License: MIT
Keywords: keras,ascii
Platform: UNKNOWN
Classifier: Development Status :: 3 - Alpha
Classifier: Framework :: Jupyter
Classifier: Intended Audience :: Education
Classifier: Intended Audience :: Science/Research
Classifier: Topic :: Scientific/Engineering
Classifier: Topic :: Scientific/Engineering :: Artificial Intelligence
Classifier: Topic :: Scientific/Engineering :: Visualization
Classifier: License :: OSI Approved :: MIT License
Classifier: Programming Language :: Python :: 2
Classifier: Programming Language :: Python :: 3
